README.md
setup.py
onap_dcae_cbs_docker_client/__init__.py
onap_dcae_cbs_docker_client/client.py
onap_dcae_cbs_docker_client/exceptions.py
onap_dcae_cbs_docker_client.egg-info/PKG-INFO
onap_dcae_cbs_docker_client.egg-info/SOURCES.txt
onap_dcae_cbs_docker_client.egg-info/dependency_links.txt
onap_dcae_cbs_docker_client.egg-info/requires.txt
onap_dcae_cbs_docker_client.egg-info/top_level.txt