Metadata-Version: 1.0
Name: onap-dcae-cbs-docker-client
Version: 2.1.1
Summary: very lightweight client for a DCAE dockerized component to get it's config from the CBS
Home-page: https://gerrit.onap.org/r/#/admin/projects/dcaegen2/utils
Author: Tommy Carpenter
Author-email: tommy@research.att.com
License: Apache 2
Platform: UNKNOWN
